bayesian_cut/__init__.py
bayesian_cut/cuts/__init__.py
bayesian_cut/cuts/bayesian_models.py
bayesian_cut/cuts/object_test.py
bayesian_cut/cuts/spectral_models.py
bayesian_cut/data/__init__.py
bayesian_cut/data/load.py
bayesian_cut/tests/__init__.py
bayesian_cut/tests/load_data.py
bayesian_cut/tests/test_bayesian_cut.py
bayesian_cut/utils/__init__.py
bayesian_cut/utils/utils.py
bayesian_cut-0.1.2b0.dist-info/LICENSE.txt
bayesian_cut-0.1.2b0.dist-info/METADATA
bayesian_cut-0.1.2b0.dist-info/WHEEL
bayesian_cut-0.1.2b0.dist-info/top_level.txt
bayesian_cut-0.1.2b0.dist-info/RECORD
