Metadata-Version: 2.1
Name: bayesian-cut
Version: 0.1.2b0
Summary: An implementation of bayesian cut methods
Home-page: https://github.com/DTUComputeCognitiveSystems/bayesian_cut
Author: Laurent Vermue, Maciej Korzepa, Petr Taborsky, Morten Mørup
Author-email: <lauve@dtu.dk>, <mjko@dtu.dk>, <ptab@dtu.dk>, <mmor@dtu.dk>
License: new BSD
Platform: UNKNOWN
Classifier: Intended Audience :: Science/Research
Classifier: Intended Audience :: Developers
Classifier: License :: OSI Approved
Classifier: Programming Language :: Python
Classifier: Topic :: Software Development
Classifier: Topic :: Scientific/Engineering
Classifier: Operating System :: Microsoft :: Windows
Classifier: Operating System :: POSIX
Classifier: Operating System :: Unix
Classifier: Operating System :: MacOS
Classifier: Programming Language :: Python :: 3.5
Classifier: Programming Language :: Python :: 3.6
Classifier: Programming Language :: Python :: 3.7
Classifier: Development Status :: 4 - Beta
Requires-Python: >=3.5
Requires-Dist: numpy (>=1.13.3)
Requires-Dist: scipy (>=1.0.0)
Requires-Dist: scikit-learn (>=0.20.0)
Requires-Dist: networkx (>=2.0)
Requires-Dist: joblib (>=0.12.3)
Provides-Extra: docs
Requires-Dist: sphinx (>=1.6) ; extra == 'docs'
Requires-Dist: sphinx-rtd-theme ; extra == 'docs'
Requires-Dist: nbsphinx ; extra == 'docs'
Requires-Dist: nbsphinx-link ; extra == 'docs'
Provides-Extra: extras
Requires-Dist: matplotlib ; extra == 'extras'
Requires-Dist: plotly ; extra == 'extras'
Requires-Dist: naturalneighbor ; extra == 'extras'
Requires-Dist: seaborn ; extra == 'extras'
Provides-Extra: tests
Requires-Dist: pytest ; extra == 'tests'
